git_tag_deploy/__init__.py
git_tag_deploy/cli.py
git_tag_deploy/deployer.py
git_tag_deploy/server.py
git_tag_deploy-0.2.1.dist-info/licenses/LICENSE
git_tag_deploy-0.2.1.dist-info/METADATA
git_tag_deploy-0.2.1.dist-info/WHEEL
git_tag_deploy-0.2.1.dist-info/entry_points.txt
git_tag_deploy-0.2.1.dist-info/top_level.txt
git_tag_deploy-0.2.1.dist-info/RECORD
