Metadata-Version: 2.4
Name: git-tag-deploy
Version: 0.2.1
Summary: Dev tool to deploy git-tagged versions of a FastAPI app
Author-email: Tenbatsu24 <puruvaish24@outlook.com>
License-Expression: Apache-2.0
Project-URL: Homepage, https://github.com/Tenbatsu24/git-tag-deployment
Project-URL: Documentation, https://github.com/Tenbatsu24/git-tag-deployment#readme
Keywords: fastapi,deployment,git,automation,cli
Classifier: Programming Language :: Python :: 3
Classifier: Operating System :: OS Independent
Classifier: Development Status :: 4 - Beta
Classifier: Intended Audience :: Developers
Classifier: Topic :: Software Development :: Build Tools
Classifier: Topic :: Software Development :: Libraries :: Application Frameworks
Classifier: Topic :: Software Development :: Libraries :: Python Modules
Classifier: Topic :: Internet :: WWW/HTTP :: Dynamic Content
Classifier: Topic :: Utilities
Requires-Python: >=3.10
License-File: LICENSE
Requires-Dist: pyyaml
Requires-Dist: fastapi
Requires-Dist: uvicorn
Dynamic: license-file
